DSTS/__init__.py
DSTS/calibration1.py
DSTS/calibration2.py
DSTS/dsts.py
DSTS/mixup.py
DSTS/utils.py
DSTS/y1_generation.py
dsts-2.1.2.dist-info/LICENSE
dsts-2.1.2.dist-info/METADATA
dsts-2.1.2.dist-info/WHEEL
dsts-2.1.2.dist-info/top_level.txt
dsts-2.1.2.dist-info/RECORD
