Metadata-Version: 2.1
Name: DSTS
Version: 2.1.2
Summary: Official Python package implementation of the paper Doubly Structured Data Synthesis for Time-series Energy Use Data
Author-email: Changwook Lee <changwook1410@gmail.com>
Project-URL: Homepage, https://github.com/chomgid/DSTS
Project-URL: Source, https://github.com/chomgid/DSTS
Classifier: Programming Language :: Python :: 3
Classifier: License :: OSI Approved :: MIT License
Classifier: Operating System :: OS Independent
Requires-Python: <3.10,>=3.6
License-File: LICENSE
Requires-Dist: pandas>=2.0.0
Requires-Dist: scikit-learn>=1.2.0
Requires-Dist: tensorflow<=2.13.1
Requires-Dist: tqdm>=4.64.1
Requires-Dist: torch>=2.0.1
Requires-Dist: seaborn>=0.12.2
